dpytils/__init__.py
dpytils-0.0.5.dist-info/LICENSE
dpytils-0.0.5.dist-info/METADATA
dpytils-0.0.5.dist-info/WHEEL
dpytils-0.0.5.dist-info/top_level.txt
dpytils-0.0.5.dist-info/RECORD
