Metadata-Version: 2.1
Name: dpytils
Version: 0.0.5
Summary: A package with all sorts of utilities for discord.py.
Home-page: https://github.com/TymanWasTaken/dpytils
Author: Tyman
License: MIT License
Project-URL: Issue Tracker, https://github.com/TymanWasTaken/dpytils/issues
Project-URL: Documentation, https://github.com/TymanWasTaken/dpytils/wiki
Platform: UNKNOWN
Requires-Dist: setuptools (>=41.2.0)
Requires-Dist: discord.py (>=1.3)
